LICENSE
MANIFEST.in
README.rst
setup.py
treq_kerberos/__init__.py
treq_kerberos.egg-info/PKG-INFO
treq_kerberos.egg-info/SOURCES.txt
treq_kerberos.egg-info/dependency_links.txt
treq_kerberos.egg-info/not-zip-safe
treq_kerberos.egg-info/requires.txt
treq_kerberos.egg-info/top_level.txt