Metadata-Version: 1.1
Name: treq-kerberos
Version: 1.2.0
Summary: Kerberos auth for Twisted's treq
Home-page: https://github.com/ktdreyer/treq-kerberos
Author: Ken Dreyer
Author-email: ktdreyer@ktdreyer.com
License: MIT
Keywords: twisted,treq,kerberos
Platform: UNKNOWN
Classifier: Development Status :: 4 - Beta
Classifier: Framework :: Twisted
Classifier: Intended Audience :: Developers
Classifier: License :: OSI Approved :: MIT License
Classifier: Operating System :: OS Independent
Classifier: Programming Language :: Python :: 2.7
Classifier: Programming Language :: Python :: 3.6
